odoo/addons/hr_attendance_calendar_view/README.rst
odoo/addons/hr_attendance_calendar_view/__init__.py
odoo/addons/hr_attendance_calendar_view/__manifest__.py
odoo/addons/hr_attendance_calendar_view/i18n/hr_attendance_calendar_view.pot
odoo/addons/hr_attendance_calendar_view/i18n/it.po
odoo/addons/hr_attendance_calendar_view/i18n/tr.po
odoo/addons/hr_attendance_calendar_view/readme/CONTRIBUTORS.md
odoo/addons/hr_attendance_calendar_view/readme/DESCRIPTION.md
odoo/addons/hr_attendance_calendar_view/static/description/icon.png
odoo/addons/hr_attendance_calendar_view/static/description/index.html
odoo/addons/hr_attendance_calendar_view/views/hr_attendance_calendar_views.xml
odoo_addon_hr_attendance_calendar_view-17.0.1.0.0.4.dist-info/METADATA
odoo_addon_hr_attendance_calendar_view-17.0.1.0.0.4.dist-info/WHEEL
odoo_addon_hr_attendance_calendar_view-17.0.1.0.0.4.dist-info/top_level.txt
odoo_addon_hr_attendance_calendar_view-17.0.1.0.0.4.dist-info/RECORD
